seasonable/__init__.py
seasonable/buttondown.py
seasonable/client.py
seasonable/fastmail.py
seasonable/habitica.py
seasonable/todoist.py
seasonable/toggl.py
seasonable/ui.py
seasonable/examples/__init__.py
seasonable/examples/buttondown.py
seasonable/examples/fastmail.py
seasonable/examples/habitica.py
seasonable/examples/todoist.py
seasonable/examples/toggl.py
seasonable/tests/__init__.py
seasonable-2021.9.1.dist-info/METADATA
seasonable-2021.9.1.dist-info/WHEEL
seasonable-2021.9.1.dist-info/top_level.txt
seasonable-2021.9.1.dist-info/RECORD
